{
    "asset": {
        "format": "jpg",
        "id": "5d0589d6247c85001a7a6f3601b9d49f",
        "name": "10098.jpg",
        "path": "file:C:/Users/viers/OneDrive/Bureaublad/ResearchProject/researchproject/FaceDetectionYolo/data/dogFacesFull/DogVsCatsDataset/Images/10098.jpg",
        "size": {
            "width": 500,
            "height": 375
        },
        "state": 2,
        "type": 1
    },
    "regions": [
        {
            "id": "w1LM6cOdx",
            "type": "RECTANGLE",
            "tags": [
                "Face"
            ],
            "boundingBox": {
                "height": 228.18747972094206,
                "width": 190.21152605026276,
                "left": 145.084627640587,
                "top": 115.78182559857444
            },
            "points": [
                {
                    "x": 145.084627640587,
                    "y": 115.78182559857444
                },
                {
                    "x": 335.29615369084974,
                    "y": 115.78182559857444
                },
                {
                    "x": 335.29615369084974,
                    "y": 343.96930531951654
                },
                {
                    "x": 145.084627640587,
                    "y": 343.96930531951654
                }
            ]
        }
    ],
    "version": "2.2.0"
}