{
    "asset": {
        "format": "jpg",
        "id": "5faabb3baed683f82e59d680cc7128b7",
        "name": "thumbnail_85959.jpg",
        "path": "file:C:/Users/viers/OneDrive/Bureaublad/ResearchProject/researchproject/FaceDetectionYolo/data/dogFacesFull/OwnPictures/Images/thumbnail_85959.jpg",
        "size": {
            "width": 480,
            "height": 640
        },
        "state": 2,
        "type": 1
    },
    "regions": [
        {
            "id": "QeZDCvjHe",
            "type": "RECTANGLE",
            "tags": [
                "Face"
            ],
            "boundingBox": {
                "height": 276.5736141682113,
                "width": 237.66906964616808,
                "left": 121.02774451483312,
                "top": 143.37084666792168
            },
            "points": [
                {
                    "x": 121.02774451483312,
                    "y": 143.37084666792168
                },
                {
                    "x": 358.6968141610012,
                    "y": 143.37084666792168
                },
                {
                    "x": 358.6968141610012,
                    "y": 419.944460836133
                },
                {
                    "x": 121.02774451483312,
                    "y": 419.944460836133
                }
            ]
        }
    ],
    "version": "2.2.0"
}